{
  "tile": "Elastic Runtime",
  "version": "1.8",
  "size": "large",
  "display_name": "Large",
  "description": "Large Size of PCF Foundation and Elastic Runtime for Multiple Dev/Test/Production Env",
  "avg_ai_ram": 2,
  "avg_ai_disk": 3,
  "ai_packs": 4,
  "az_count": 3,
  "extra_runners_per_az": 0,
  "is_default": false,
  "is_disabled": false,
  "can_customize": false,
  "priority": 3,
  "vms":
  [
    {
      "vm": "Ops Manager VM",
      "instances": 1,
      "persistent_disk": 50,
      "dynamic_ips": 0,
      "static_ips": 1,
      "instance_type": "n1-standard-4",
      "singleton": true
    },
    {
      "vm": "Ops Manager Director",
      "instances": 1,
      "persistent_disk": 50,
      "dynamic_ips": 1,
      "static_ips": 1,
      "instance_type": "n1-standard-4",
      "singleton": true
    },
    {
      "vm": "Consul",
      "instances": 3,
      "persistent_disk": 2,
      "dynamic_ips": 1,
      "static_ips": 1,
      "instance_type": "n1-standard-1",
      "singleton": false
    },
    {
      "vm": "NATS",
      "instances": 3,
      "persistent_disk": 0,
      "dynamic_ips": 1,
      "static_ips": 1,
      "instance_type": "n1-standard-1",
      "singleton": false
    },
    {
      "vm": "etcd",
      "instances": 3,
      "persistent_disk": 2,
      "dynamic_ips": 1,
      "static_ips": 0,
      "instance_type": "n1-standard-1",
      "singleton": false
    },
    {
      "vm": "Diego BBS",
      "instances": 3,
      "persistent_disk": 2,
      "dynamic_ips": 1,
      "static_ips": 0,
      "instance_type": "n1-standard-1",
      "singleton": false
    },
    {
      "vm": "NFS Server",
      "instances": 1,
      "persistent_disk": 100,
      "dynamic_ips": 1,
      "static_ips": 1,
      "instance_type": "n1-standard-1",
      "singleton": false
    },
    {
      "vm": "Router",
      "instances": 3,
      "persistent_disk": 0,
      "dynamic_ips": 1,
      "static_ips": 1,
      "instance_type": "n1-standard-1",
      "singleton": false
    },
    {
      "vm": "MySQL Proxy",
      "instances": 3,
      "persistent_disk": 0,
      "dynamic_ips": 1,
      "static_ips": 1,
      "instance_type": "n1-standard-1",
      "singleton": false
    },
    {
      "vm": "MySQL Server",
      "instances": 3,
      "persistent_disk": 100,
      "dynamic_ips": 1,
      "static_ips": 0,
      "instance_type": "n1-standard-4",
      "singleton": false
    },
    {
      "vm": "MySQL Backup & Prepare",
      "instances": 1,
      "persistent_disk": 250,
      "dynamic_ips": 1,
      "static_ips": 0,
      "instance_type": "n1-standard-8",
      "singleton": false
    },
    {
      "vm": "Cloud Controller",
      "instances": 3,
      "persistent_disk": 0,
      "dynamic_ips": 1,
      "static_ips": 0,
      "instance_type": "n1-standard-1",
      "singleton": false
    },
    {
      "vm": "Clock Global",
      "instances": 1,
      "persistent_disk": 0,
      "dynamic_ips": 1,
      "static_ips": 0,
      "instance_type": "n1-standard-1",
      "singleton": true
    },
    {
      "vm": "Cloud Controller Worker",
      "instances": 3,
      "persistent_disk": 0,
      "dynamic_ips": 1,
      "static_ips": 0,
      "instance_type": "n1-standard-1",
      "singleton": false
    },
    {
      "vm": "UAA",
      "instances": 3,
      "persistent_disk": 0,
      "dynamic_ips": 1,
      "static_ips": 0,
      "instance_type": "n1-standard-1",
      "singleton": false
    },
    {
      "vm": "Diego Brain",
      "instances": 3,
      "persistent_disk": 1,
      "dynamic_ips": 1,
      "static_ips": 0,
      "instance_type": "n1-standard-1",
      "singleton": false
    },
    {
      "vm": "Diego Cell",
      "instances": 16,
      "persistent_disk": 64,
      "dynamic_ips": 1,
      "static_ips": 0,
      "instance_type": "n1-highmem-4",
      "valid_instance_types": [
        "n1-highmem-4"
      ],
      "singleton": false
    },
    {
      "vm": "Doppler Server",
      "instances": 3,
      "persistent_disk": 0,
      "dynamic_ips": 1,
      "static_ips": 1,
      "instance_type": "n1-standard-1",
      "singleton": false
    },
    {
      "vm": "Loggregator Traffic Controller",
      "instances": 3,
      "persistent_disk": 0,
      "dynamic_ips": 1,
      "static_ips": 1,
      "instance_type": "n1-standard-1",
      "singleton": false
    },
    {
      "vm": "Compilation",
      "instances": 1,
      "persistent_disk": 0,
      "dynamic_ips": 1,
      "static_ips": 0,
      "instance_type": "n1-standard-1",
      "singleton": false,
      "valid_instance_types": [
        "n1-standard-1"
      ]
    },
    {
      "vm": "Errands",
      "instances": 13,
      "persistent_disk": 0,
      "dynamic_ips": 1,
      "static_ips": 0,
      "instance_type": "n1-standard-1",
      "singleton": false,
      "valid_instance_types": [
        "n1-standard-1"
      ]
    }
  ]
}
